dmenu_extended/__init__.py
dmenu_extended/install_systemd_service.py
dmenu_extended/main.py
dmenu_extended-1.3.0.dist-info/LICENSE
dmenu_extended-1.3.0.dist-info/METADATA
dmenu_extended-1.3.0.dist-info/WHEEL
dmenu_extended-1.3.0.dist-info/entry_points.txt
dmenu_extended-1.3.0.dist-info/top_level.txt
dmenu_extended-1.3.0.dist-info/RECORD
