Metadata-Version: 2.1
Name: dmenu_extended
Version: 1.3.0
Summary: A wrapper for dmenu that implements plugins and fast file/folder searching
Author-email: Mark Hedley Jones <markhedleyjones@gmail.com>
License: The MIT License (MIT)
Project-URL: Homepage, https://github.com/MarkHedleyJones/dmenu-extended
Project-URL: Bug Tracker, https://github.com/MarkHedleyJones/dmenu-extended/issues
Classifier: Programming Language :: Python :: 3
Classifier: License :: OSI Approved :: MIT License
Classifier: Operating System :: OS Independent
Requires-Python: >=3.7
License-File: LICENSE
Requires-Dist: setuptools >=61.0
